safety_agent/__init__.py
safety_agent/client.py
safety_agent/schemas.py
safety_agent/types.py
safety_agent/prompts/__init__.py
safety_agent/prompts/guard.py
safety_agent/prompts/redact.py
safety_agent/providers/__init__.py
safety_agent/providers/anthropic.py
safety_agent/providers/bedrock.py
safety_agent/providers/fireworks.py
safety_agent/providers/google.py
safety_agent/providers/groq.py
safety_agent/providers/openai.py
safety_agent/providers/openrouter.py
safety_agent/providers/superagent.py
safety_agent/providers/types.py
safety_agent/providers/vercel.py
safety_agent/utils/__init__.py
safety_agent/utils/input_processor.py
safety_agent-0.1.2.dist-info/METADATA
safety_agent-0.1.2.dist-info/WHEEL
safety_agent-0.1.2.dist-info/RECORD
