Metadata-Version: 2.4
Name: safety-agent
Version: 0.1.2
Summary: A lightweight Python guardrail SDK for content safety
Project-URL: Homepage, https://superagent.sh
Project-URL: Documentation, https://docs.superagent.sh
Project-URL: Repository, https://github.com/superagent-ai/superagent
Author: Superagent AI
License-Expression: MIT
Keywords: ai,content-moderation,guardrail,llm,safety
Classifier: Development Status :: 4 - Beta
Classifier: Intended Audience :: Developers
Classifier: License :: OSI Approved :: MIT License
Classifier: Programming Language :: Python :: 3
Classifier: Programming Language :: Python :: 3.10
Classifier: Programming Language :: Python :: 3.11
Classifier: Programming Language :: Python :: 3.12
Classifier: Programming Language :: Python :: 3.13
Classifier: Topic :: Scientific/Engineering :: Artificial Intelligence
Classifier: Topic :: Software Development :: Libraries :: Python Modules
Requires-Python: >=3.10
Requires-Dist: daytona-sdk>=0.129.0
Requires-Dist: httpx>=0.27.0
Requires-Dist: pypdf>=5.0.0
